xton/common.py
xton/core.py
xton/main.py
xton/stdlib.func
xton-0.0.4.dist-info/LICENSE
xton-0.0.4.dist-info/METADATA
xton-0.0.4.dist-info/WHEEL
xton-0.0.4.dist-info/entry_points.txt
xton-0.0.4.dist-info/top_level.txt
xton-0.0.4.dist-info/RECORD
